excel/__init__.py
excel/remove_excel_ruby.py
word/__init__.py
word/remove_word_ruby.py
office_ruby_remover-0.1.1.dist-info/LICENSE
office_ruby_remover-0.1.1.dist-info/METADATA
office_ruby_remover-0.1.1.dist-info/WHEEL
office_ruby_remover-0.1.1.dist-info/entry_points.txt
office_ruby_remover-0.1.1.dist-info/top_level.txt
office_ruby_remover-0.1.1.dist-info/RECORD
