Metadata-Version: 2.1
Name: office-ruby-remover
Version: 0.1.1
Summary: Microsoft Office（Word/Excel）ドキュメントからルビ（ふりがな）を削除するツール
Home-page: https://github.com/abachan/office-ruby-remover
Author: abachan
Author-email: aiba1114@cl.cilas.net
Project-URL: Bug Reports, https://github.com/abachan/office-ruby-remover/issues
Project-URL: Source, https://github.com/abachan/office-ruby-remover
Keywords: office,word,excel,ruby,furigana,document,processing
Classifier: Development Status :: 4 - Beta
Classifier: Intended Audience :: Developers
Classifier: Intended Audience :: Information Technology
Classifier: License :: OSI Approved :: MIT License
Classifier: Operating System :: OS Independent
Classifier: Programming Language :: Python :: 3
Classifier: Programming Language :: Python :: 3.8
Classifier: Programming Language :: Python :: 3.9
Classifier: Programming Language :: Python :: 3.10
Classifier: Programming Language :: Python :: 3.11
Classifier: Topic :: Office/Business
Classifier: Topic :: Software Development :: Libraries :: Python Modules
Classifier: Topic :: Text Processing :: Markup
Requires-Python: >=3.8
License-File: LICENSE
Requires-Dist: python-docx>=0.8.11
Requires-Dist: openpyxl>=3.0.0
